{
  "DM_MUZZLE": "owner",
  "STATUS_COALESCE_TITLES": "Periodic Status",
  "STATUS_EDIT_WINDOW_SEC": 43200,
  "COGS_FORCE_ENABLE": [
    "satpambot.bot.modules.discord_bot.cogs.status_pin_updater",
    "satpambot.bot.modules.discord_bot.cogs.a08_public_clearchat",
    "satpambot.bot.modules.discord_bot.cogs.imagephish_ref_indexer_v2"
  ],
  "PHASH_DB_PATH": "data/phash/SATPAMBOT_PHASH_DB_V1.json",
  "PHASH_INDEX_LOG_CHANNEL_ID": 1400375184048787566,
  "PHASH_INDEX_THREAD_NAMES": [
    "imagephising"
  ],
  "PHASH_INDEX_THREAD_IDS": "",
  "PHASH_INDEX_BACKFILL_DAYS": 14,
  "PHASH_INDEX_SCAN_INTERVAL": 600,
  "PHASH_INDEX_ALLOW_EXTS": "png,jpg,jpeg,gif,webp",
  "PHISH_ENFORCE_MODE": "always",
  "PHISH_DELETE_MESSAGE_DAYS": 7,
  "PHISH_BAN_REASON_PRESET": "compromised",
  "PHISH_BAN_REASON_SUFFIX": "Anti-Image Guard (armed)",
  "PHISH_MIME_SNIFF_ENABLE": true,
  "PHISH_STRONG_DISTANCE": 4,
  "PHISH_MODERATE_DISTANCE": 8,
  "PHISH_MIN_LABELED_DUPLICATES": 2,
  "PHISH_ACTION_STRONG": "ban",
  "PHISH_ACTION_MODERATE": "delete",
  "PHISH_TIMEOUT_SECS": 0,
  "PHISH_ENFORCE_REQUIRE_LABEL": "",
  "PHISH_LOG_CHANNEL_ID": 1400375184048787566,
  "PHISH_SOURCE_CHANNEL_IDS": "1426397317598154844"
}